Rbeast-0.1.23.dist-info/RECORD
Rbeast-0.1.23.dist-info/LICENSE
Rbeast-0.1.23.dist-info/WHEEL
Rbeast-0.1.23.dist-info/top_level.txt
Rbeast-0.1.23.dist-info/METADATA
Rbeast/beast123.py
Rbeast/plotbeast.py
Rbeast/printbeast.py
Rbeast/beast.py
Rbeast/__init__.py
Rbeast/cvt_to_numpy.py
Rbeast/beast_irreg.py
Rbeast/extractbeast.py
Rbeast/Rbeast.cpython-38-darwin.so
Rbeast/load_example.py
Rbeast/data/googletrend.csv
Rbeast/data/ohio.csv
Rbeast/data/covid19.csv
Rbeast/data/co2.csv
Rbeast/data/simdata.csv
Rbeast/data/imagestack.npy
Rbeast/data/yellowstone.csv
Rbeast/data/nile.csv
