Metadata-Version: 2.1
Name: Rbeast
Version: 0.1.23
Summary: Bayesian changepoint detection and time series decomposition
Home-page: https://github.com/zhaokg/Rbeast
Author: Kaiguang Zhao
Author-email: zhao.1423@osu.edu
Keywords: changepoint,structural breaks,time series decompositiontime series analysis,trend analysis
Classifier: Programming Language :: Python
Classifier: Programming Language :: Python :: 3.7
Classifier: Programming Language :: Python :: 3.8
Classifier: Programming Language :: Python :: 3.9
Classifier: Programming Language :: Python :: 3.10
Classifier: Programming Language :: Python :: 3.11
Classifier: Programming Language :: Python :: 3.12
Classifier: Intended Audience :: Science/Research
Classifier: Topic :: Scientific/Engineering :: Hydrology
Classifier: Topic :: Scientific/Engineering :: Atmospheric Science
Classifier: Topic :: Scientific/Engineering :: Artificial Intelligence
Classifier: Topic :: Scientific/Engineering
Classifier: License :: OSI Approved :: MIT License
Requires-Python: >=3.5
License-File: LICENSE
Requires-Dist: numpy >=1.10.0
